concord/__init__.py
concord/client.py
concord/constants.py
concord/context.py
concord/exceptions.py
concord/ext/base/__init__.py
concord/ext/base/event.py
concord/ext/base/filters/__init__.py
concord/ext/base/filters/command.py
concord/ext/base/filters/common.py
concord/extension.py
concord/middleware.py
concord/utils.py
cncrd-0.10.1.dist-info/LICENSE
cncrd-0.10.1.dist-info/WHEEL
cncrd-0.10.1.dist-info/METADATA
cncrd-0.10.1.dist-info/RECORD
