Metadata-Version: 2.1
Name: cncrd
Version: 0.10.1
Summary: Middleware-based event processing library for Discord
Home-page: https://github.com/narimanized/concord
License: MIT
Keywords: discord,concord,bot
Author: Nariman Safiulin
Author-email: woofilee@gmail.com
Requires-Python: >=3.6,<4.0
Classifier: Development Status :: 4 - Beta
Classifier: Environment :: Console
Classifier: Intended Audience :: Developers
Classifier: License :: OSI Approved :: MIT License
Classifier: Natural Language :: English
Classifier: Natural Language :: Russian
Classifier: Operating System :: OS Independent
Classifier: Programming Language :: Python :: 3
Classifier: Programming Language :: Python :: 3.6
Classifier: Programming Language :: Python :: 3.7
Classifier: Topic :: Software Development :: Libraries :: Python Modules
Requires-Dist: discord.py
Project-URL: Repository, https://github.com/narimanized/concord
